streamlit_swipecards/__init__.py
streamlit_swipecards/frontend/index.html
streamlit_swipecards/frontend/main.js
streamlit_swipecards/frontend/streamlit-component-lib.js
streamlit_swipecards/frontend/style.css
streamlit_swipecards-0.4.8.dist-info/licenses/LICENSE
streamlit_swipecards-0.4.8.dist-info/METADATA
streamlit_swipecards-0.4.8.dist-info/WHEEL
streamlit_swipecards-0.4.8.dist-info/top_level.txt
streamlit_swipecards-0.4.8.dist-info/RECORD
