Metadata-Version: 2.4
Name: streamlit-swipecards
Version: 0.4.8
Summary: Streamlit Swipecards allow you to add interactive swipeable cards to your app. Supports both image cards and table row swiping with cell highlighting.
Author: Julian
Author-email: julien.playsde@gmail.com
Requires-Python: >=3.7
License-File: LICENSE
Requires-Dist: streamlit>=1.2
Requires-Dist: jinja2
Requires-Dist: pandas
Requires-Dist: openpyxl
Dynamic: author
Dynamic: author-email
Dynamic: description
Dynamic: description-content-type
Dynamic: license-file
Dynamic: requires-dist
Dynamic: requires-python
Dynamic: summary
